ecpat1/__init__.py
ecpat1/api.py
ecpat1/const.py
ecpat1/errors.py
ecpatestapitest-0.0.9.dist-info/LICENSE
ecpatestapitest-0.0.9.dist-info/METADATA
ecpatestapitest-0.0.9.dist-info/WHEEL
ecpatestapitest-0.0.9.dist-info/top_level.txt
ecpatestapitest-0.0.9.dist-info/RECORD
