Metadata-Version: 2.1
Name: ecpatestapitest
Version: 0.0.9
Summary: Ecowitt get data
Author: Ecowitt_1
Author-email: 369532361@qq.com
Classifier: Programming Language :: Python :: 3
Classifier: License :: OSI Approved :: MIT License
Classifier: Operating System :: OS Independent
License-File: LICENSE
